{
  "Name": "Hardened Bear Leather",
  "Profession": "Leatherworking",
  "Category": "variant",
  "variantOf": "Hardened Patchwork Leather",
  "Attribute": "Attack power",
  "Impact": 0.5,
  "Chance": null,
  "Difficulty": null,
  "Components": [
    {
      "name": "Bear Hide",
      "amount": 2,
      "required": false,
      "wildcard": false
    },
    {
      "name": "Bear Hide",
      "amount": 2,
      "required": false,
      "wildcard": false
    },
    {
      "name": "Bear Hide",
      "amount": 2,
      "required": false,
      "wildcard": false
    }
  ]
}
