{
  "name": "Padded Sharp Elk Leather",
  "parent": "Reinforced Padding",
  "attribute": "Damage bonus: Piercing",
  "impact": 0.06,
  "success_chance": null,
  "difficulty": null,
  "components": [
    {
      "name": "Elk Hide",
      "amount": 2,
      "required": true
    },
    {
      "name": "Elk Hide",
      "amount": 2,
      "required": true
    },
    {
      "name": "Cat Hide",
      "amount": 2,
      "required": true
    },
    {
      "name": "Ore",
      "amount": 1,
      "required": true
    },
    {
      "name": "Specialty Seal",
      "amount": 1,
      "required": false
    }
  ]
}
