{
  "Name": "Gold Bar",
  "Profession": "Blacksmith",
  "Category": "variant",
  "variantOf": "Plain Metal Bar",
  "Attribute": "Support power",
  "Impact": 0.4,
  "Chance": null,
  "Difficulty": null,
  "Components": [
    {
      "name": "Gold",
      "amount": 3,
      "required": false,
      "wildcard": false
    },
    {
      "name": "Gold",
      "amount": 3,
      "required": false,
      "wildcard": false
    },
    {
      "name": "Gold",
      "amount": 3,
      "required": false,
      "wildcard": false
    }
  ]
}
